{
  "kind": "mhxy-shikong.execution-state",
  "schemaVersion": 1,
  "revision": 361,
  "generation": 1,
  "updatedAt": "2026-07-13T09:11:57Z",
  "taskId": "MHXY-AUTOMATION-WORKBENCH",
  "objective": "交付一个用户操作量低、可自定义编排、可持久化、多窗口并行且不影响前台鼠标键盘的梦幻西游后台自动化工作台。",
  "sourcePriority": [
    "current_source_git_and_runtime",
    "persisted_test_screenshot_report_and_hash_evidence",
    "docs/execution/state.json",
    "docs/execution/STATUS.md",
    "codex_thread_history"
  ],
  "sourceDocuments": {
    "masterPlan": "docs/project-audit-and-master-plan.md",
    "protocol": "docs/execution/PROTOCOL.md",
    "status": "docs/execution/STATUS.md"
  },
  "run": {
    "runId": "RUN-20260710-CONTINUITY-BASELINE",
    "attempt": 1,
    "primaryThreadId": "019f5a42-5766-7be3-9861-f979ab529d26",
    "previousThreadId": "019f42cc-2993-7681-b8d2-5269cf5447e1",
    "startedAt": "2026-07-10T08:31:39Z",
    "owner": "primary-agent"
  },
  "overallStatus": "active",
  "currentPhaseId": "P3",
  "phaseStatus": "in_progress",
  "actionStatus": "succeeded",
  "acceptanceLevel": "design",
  "activeSlice": {
    "id": "P3-S5",
    "title": "Current-commit app launch gate with specialized verifier",
    "status": "verified",
    "startedAt": "2026-07-13T08:48:21Z",
    "scope": [
      "scripts/verify_app_runtime_launch.py",
      "scripts/execution_progress.py",
      "scripts/test_execution_progress.py",
      "package.json"
    ],
    "nonGoals": [
      "Do not send live game input",
      "Do not migrate AppData",
      "Do not force-push"
    ],
    "safetyBoundaries": [
      "Only start process registered via process_start action with ownership evidence",
      "Stop only owned managed processes from this run"
    ],
    "acceptanceCriteria": [
      {
        "id": "P3-S5-C1",
        "text": "specialized app_runtime verifier is allowlisted and rejects unowned/mismatched exe",
        "status": "passed",
        "evidenceIds": [
          "EVD-0115",
          "EVD-0117",
          "EVD-0119"
        ],
        "requiredEvidenceCategories": [
          "test"
        ]
      },
      {
        "id": "P3-S5-C2",
        "text": "current HEAD release/debug app process is started owned and observed present",
        "status": "passed",
        "evidenceIds": [
          "EVD-0114",
          "EVD-0121"
        ],
        "requiredEvidenceCategories": [
          "app_runtime"
        ]
      },
      {
        "id": "P3-S5-C3",
        "text": "process ownership evidence includes command/cwd/pid and head fingerprint",
        "status": "passed",
        "evidenceIds": [
          "EVD-0115",
          "EVD-0117",
          "EVD-0119"
        ],
        "requiredEvidenceCategories": [
          "test"
        ]
      },
      {
        "id": "P3-S5-C4",
        "text": "core regression remains green after verifier wiring",
        "status": "passed",
        "evidenceIds": [
          "EVD-0115",
          "EVD-0116",
          "EVD-0117",
          "EVD-0118",
          "EVD-0119",
          "EVD-0120"
        ],
        "requiredEvidenceCategories": [
          "build",
          "test"
        ]
      }
    ],
    "nextAction": "Begin P3-S6 or P4-S1: match overlay UI and/or home-vitality capture binding without live input; keep owned app or stop via process_stop"
  },
  "phases": [
    {
      "id": "P0",
      "title": "数据保护与可重复基线",
      "status": "verified",
      "summary": "保护真实 v6 工作区、建立匿名迁移 fixture 和可重复验证基线。"
    },
    {
      "id": "P1",
      "title": "运行安全硬化",
      "status": "verified",
      "summary": "消除窗口身份、权限、误跑和输入安全 P0/P1 风险。"
    },
    {
      "id": "P2",
      "title": "工作台可达性与单步调试",
      "status": "verified",
      "summary": "重构默认窗口下的操作路径，建立每个功能即时可见、可测的工作台。"
    },
    {
      "id": "P3",
      "title": "严格捕获和视觉引擎",
      "status": "in_progress",
      "summary": "修复捕获、ROI、模板、OCR 和预览一致性。"
    },
    {
      "id": "P4",
      "title": "第一个真实纵向任务",
      "status": "pending",
      "summary": "以家园活力完成 UI 到游戏后置验证的真实闭环。"
    },
    {
      "id": "P5",
      "title": "持久化和素材文件化",
      "status": "pending",
      "summary": "按方案评估 SQLite/结构化 JSON，补版本迁移、原子写入和备份。"
    },
    {
      "id": "P6",
      "title": "第二至第五个真实任务",
      "status": "pending",
      "summary": "逐个纵向闭环更多真实任务，不用草稿数量代替可用性。"
    },
    {
      "id": "P7",
      "title": "双窗口并行和队列控制",
      "status": "pending",
      "summary": "验证同窗口串行、跨窗口并行、暂停继续和隔离。"
    },
    {
      "id": "P8",
      "title": "回归任务与发布门",
      "status": "pending",
      "summary": "扩展到 5-10 个可重复回归任务并完成失败矩阵。"
    },
    {
      "id": "P9",
      "title": "源码清理、稳定提交和发布",
      "status": "pending",
      "summary": "在调用链和完整验证后清理、提交、推送和发布稳定版本。"
    }
  ],
  "projectVerification": {
    "codeSurface": {
      "status": "partial",
      "note": "源码已有 15 类步骤、任务/目标/队列/readiness/失败报告等表面能力，但大型文件耦合且真实闭环不足。",
      "evidenceIds": []
    },
    "automated": {
      "status": "partial",
      "note": "P2-S2 verifier 配置、10 个测试发现和静态全回归通过；真实 Playwright UI 未执行",
      "evidenceIds": [
        "EVD-0074",
        "EVD-0075"
      ]
    },
    "currentCommitBuilt": {
      "status": "passed",
      "note": "P3-S5 rebind Vite build EVD-0120 on HEAD 4eb8f9e",
      "evidenceIds": [
        "EVD-0120"
      ]
    },
    "currentCommitAppLaunched": {
      "status": "passed",
      "note": "P3-S5 rebind owned app launch EVD-0121 pid=16244 on HEAD 4eb8f9e",
      "evidenceIds": [
        "EVD-0121"
      ]
    },
    "hwndInputActuallySent": {
      "status": "not_verified",
      "note": "当前 HEAD 没有应用 UI 到指定 hwnd 的真实输入通过证据。",
      "evidenceIds": []
    },
    "gamePostconditionObserved": {
      "status": "not_verified",
      "note": "没有绑定当前 HEAD、exe、workspace 和窗口身份的游戏后置状态证据。",
      "evidenceIds": []
    },
    "foregroundUnaffected": {
      "status": "partial",
      "note": "静态安全审计只允许 PostMessageW 路径，但尚缺当前版本实测前后台 HWND、鼠标位置和用户并行操作证据。",
      "evidenceIds": []
    },
    "secondWindowIsolationVerified": {
      "status": "not_verified",
      "note": "两个游戏进程存在，但当前 HEAD 尚未完成双窗口不同队列并行隔离验收。",
      "evidenceIds": []
    },
    "restartPersistenceVerified": {
      "status": "not_verified",
      "note": "EVD-0029 和 EVD-0030 已证明 workspace.json 与旧 workspace.json.bak 分别完成不可覆盖备份且源/目标 SHA-256 一致；真实 AppData 迁移、应用重启回读和第二次重启幂等仍未验证。",
      "evidenceIds": []
    }
  },
  "git": {
    "branch": "main",
    "observedHead": "4eb8f9e41ffad8ad703a38819fa2262d127ad0e8",
    "verifiedHead": "4eb8f9e41ffad8ad703a38819fa2262d127ad0e8",
    "upstreamHead": "3eef34f8c4b115c94e2c3cd6adb93cf329a60ef9",
    "lastKnownStableCommit": "4eb8f9e41ffad8ad703a38819fa2262d127ad0e8",
    "dirtyPaths": [
      "docs/execution/STATUS.md",
      "docs/execution/checkpoints/CP-0026-p3-s5-gates-and-verified-head.json",
      "docs/execution/events.jsonl",
      "docs/execution/evidence.jsonl",
      "docs/execution/state.json"
    ],
    "dirtyStatus": [
      " M docs/execution/STATUS.md",
      "?? docs/execution/checkpoints/CP-0026-p3-s5-gates-and-verified-head.json",
      " M docs/execution/events.jsonl",
      " M docs/execution/evidence.jsonl",
      " M docs/execution/state.json"
    ],
    "dirtyFiles": [
      {
        "path": "docs/execution/STATUS.md",
        "exists": true,
        "sha256": "0c82d152765e44402c8e40f6dfd43c9aac957d0310a6008fa48f10621568a934",
        "size": 11919
      },
      {
        "path": "docs/execution/checkpoints/CP-0026-p3-s5-gates-and-verified-head.json",
        "exists": true,
        "sha256": "25cf093a129edeebd7c305679781df249a1ccd4462c11f99a7fec5561075d4fc",
        "size": 12641
      },
      {
        "path": "docs/execution/events.jsonl",
        "exists": true,
        "sha256": "816a083af650cc44a11a94d2803b7c444163862828d1fd26c9499a9220f3aca4",
        "size": 529453
      },
      {
        "path": "docs/execution/evidence.jsonl",
        "exists": true,
        "sha256": "cdc4adc8d26cdfd53b6461835a1c521baa7a869158ee3a4691f69a06e6dce389",
        "size": 262631
      },
      {
        "path": "docs/execution/state.json",
        "exists": true,
        "sha256": "b873765aa43439bb3c2556084f248b793360b05d61c14e4ce035f5c514032c4f",
        "size": 44678
      }
    ],
    "workingTreeFingerprint": "sha256:5ddd5a0ee455fe901d2d8f445a0113e6fc9ba4a52b5b76c802032749a20b3a44",
    "dirtyEntries": [
      {
        "status": " M",
        "sourcePath": null,
        "destinationPath": "docs/execution/STATUS.md",
        "displayPath": "docs/execution/STATUS.md"
      },
      {
        "status": "??",
        "sourcePath": null,
        "destinationPath": "docs/execution/checkpoints/CP-0026-p3-s5-gates-and-verified-head.json",
        "displayPath": "docs/execution/checkpoints/CP-0026-p3-s5-gates-and-verified-head.json"
      },
      {
        "status": " M",
        "sourcePath": null,
        "destinationPath": "docs/execution/events.jsonl",
        "displayPath": "docs/execution/events.jsonl"
      },
      {
        "status": " M",
        "sourcePath": null,
        "destinationPath": "docs/execution/evidence.jsonl",
        "displayPath": "docs/execution/evidence.jsonl"
      },
      {
        "status": " M",
        "sourcePath": null,
        "destinationPath": "docs/execution/state.json",
        "displayPath": "docs/execution/state.json"
      }
    ]
  },
  "inFlightAction": null,
  "lastAction": {
    "actionId": "ACT-P3S5-APP-LAUNCH-002",
    "kind": "process_start",
    "targetIdentity": "E:\\Project\\Common\\mhxy-shikong-control\\src-tauri\\target-p3-app-launch\\debug\\mhxy-shikong-control.exe",
    "sideEffectClass": "process_start",
    "expectedPrecondition": "current HEAD debug controller exe exists with known hash; product dirty only docs/execution metadata",
    "expectedPostcondition": "owned mhxy-shikong-control process present with matching exe hash and recorded app_runtime evidence",
    "idempotencyKey": "p3s5:app-launch:4eb8f9e4:debug",
    "startedAt": "2026-07-13T09:11:04Z",
    "ownerRunId": "RUN-20260710-CONTINUITY-BASELINE",
    "ownershipEvidence": [
      "goal-externalAuthorization-local_app_run_owned_process_only",
      "cwd=E:\\Project\\Common\\mhxy-shikong-control",
      "exePath=E:\\Project\\Common\\mhxy-shikong-control\\src-tauri\\target-p3-app-launch\\debug\\mhxy-shikong-control.exe",
      "exeSha256=7bb93ec5ac2ed300a94b98dae718a2959c0251b0b6fb3586ca36734f9b17a407",
      "expectedHead=4eb8f9e41ffad8ad703a38819fa2262d127ad0e8"
    ],
    "status": "succeeded",
    "leaseTokenHash": "fa9fd24560c82d9ba59a33eedf290f43b11d929352913b08ba6f572bfb6bf08f",
    "endedAt": "2026-07-13T09:11:10Z",
    "result": "controller app launched pid=16244 exe=E:\\Project\\Common\\mhxy-shikong-control\\src-tauri\\target-p3-app-launch\\debug\\mhxy-shikong-control.exe evidence=EVD-0121",
    "verifiedEvidenceId": "EVD-0121"
  },
  "safety": {
    "realInputSent": false,
    "newApplicationStarted": false,
    "preexistingApplicationStopped": false,
    "appDataModified": false,
    "cleanupPerformed": false
  },
  "runtime": {
    "observedAt": "2026-07-13T09:11:09Z",
    "staleAfterSeconds": 300,
    "managedProcesses": [
      {
        "pid": 16244,
        "name": "mhxy-shikong-control.exe",
        "role": "controller-app",
        "exePath": "E:\\Project\\Common\\mhxy-shikong-control\\src-tauri\\target-p3-app-launch\\debug\\mhxy-shikong-control.exe",
        "cwd": "E:\\Project\\Common\\mhxy-shikong-control",
        "commandLine": "E:\\Project\\Common\\mhxy-shikong-control\\src-tauri\\target-p3-app-launch\\debug\\mhxy-shikong-control.exe",
        "creationTime": "2026-07-13T09:11:08Z",
        "ownership": "created_by_current_run",
        "ownershipEvidence": [
          "goal-externalAuthorization-local_app_run_owned_process_only",
          "cwd=E:\\Project\\Common\\mhxy-shikong-control",
          "exePath=E:\\Project\\Common\\mhxy-shikong-control\\src-tauri\\target-p3-app-launch\\debug\\mhxy-shikong-control.exe",
          "exeSha256=7bb93ec5ac2ed300a94b98dae718a2959c0251b0b6fb3586ca36734f9b17a407",
          "expectedHead=4eb8f9e41ffad8ad703a38819fa2262d127ad0e8",
          "verifier=current-app-launch-v1",
          "exeSha256=7bb93ec5ac2ed300a94b98dae718a2959c0251b0b6fb3586ca36734f9b17a407",
          "observedHead=4eb8f9e41ffad8ad703a38819fa2262d127ad0e8",
          "actionId=ACT-P3S5-APP-LAUNCH-002"
        ],
        "cleanupAllowed": true,
        "createdByRunId": "RUN-20260710-CONTINUITY-BASELINE",
        "createdByActionId": "ACT-P3S5-APP-LAUNCH-002",
        "createdAt": "2026-07-13T09:11:09Z",
        "present": true,
        "lastObservedAt": "2026-07-13T09:11:09Z"
      }
    ],
    "observedExternalProcesses": [
      {
        "pid": 42432,
        "name": "mhxy-shikong-control.exe",
        "role": "旧控制器历史线索",
        "ownership": "preexisting",
        "creationTime": "2026-07-09T15:20:29+08:00",
        "identityLimit": "本轮未停止；当前未发现",
        "cleanupAllowed": false,
        "present": false,
        "lastObservedAt": "2026-07-11T18:46:48Z",
        "observedAbsentAt": "2026-07-11T18:46:48Z"
      },
      {
        "pid": 26056,
        "name": "MyGame_x64r.exe",
        "role": "历史游戏窗口线索 A",
        "ownership": "user_preexisting",
        "creationTime": "2026-07-10T00:55:37.972416+08:00",
        "identityLimit": "ExecutablePath/CommandLine unavailable; HWND/title only read-only observed; no live authorization",
        "cleanupAllowed": false,
        "present": false,
        "lastObservedAt": "2026-07-11T18:46:49Z",
        "lastSeenAt": "2026-07-10T12:23:34Z",
        "observedAbsentAt": "2026-07-11T18:46:49Z"
      },
      {
        "pid": 52448,
        "name": "MyGame_x64r.exe",
        "role": "历史游戏窗口线索 B",
        "ownership": "user_preexisting",
        "creationTime": "2026-07-10T00:55:23.169428+08:00",
        "identityLimit": "ExecutablePath/CommandLine unavailable; HWND/title only read-only observed; no live authorization",
        "cleanupAllowed": false,
        "present": false,
        "lastObservedAt": "2026-07-11T18:46:50Z",
        "lastSeenAt": "2026-07-10T12:23:35Z",
        "observedAbsentAt": "2026-07-11T18:46:50Z"
      },
      {
        "pid": 12744,
        "name": "mhxy-shikong-control.exe",
        "role": "controller-app",
        "ownership": "task-owned",
        "present": false,
        "creationTime": "2026-07-13T08:54:11Z",
        "lastObservedAt": "2026-07-13T09:08:55Z",
        "lastSeenAt": "2026-07-13T08:54:26Z",
        "cleanupAllowed": false,
        "observedAbsentAt": "2026-07-13T09:08:55Z"
      },
      {
        "pid": 16244,
        "name": "mhxy-shikong-control.exe",
        "role": "controller-app",
        "ownership": "created_by_current_run",
        "present": true,
        "creationTime": "2026-07-13T09:11:08Z",
        "lastObservedAt": "2026-07-13T09:11:09Z",
        "lastSeenAt": "2026-07-13T09:11:09Z",
        "cleanupAllowed": false
      }
    ],
    "managedArtifacts": [
      {
        "path": "AGENTS.md",
        "ownership": "created_by_continuity_baseline",
        "cleanupAllowed": false
      },
      {
        "path": "docs/execution/",
        "ownership": "created_by_continuity_baseline",
        "cleanupAllowed": false
      },
      {
        "path": "scripts/execution_progress.py",
        "ownership": "created_by_continuity_baseline",
        "cleanupAllowed": false
      },
      {
        "path": "scripts/audit_execution_state.py",
        "ownership": "created_by_continuity_baseline",
        "cleanupAllowed": false
      }
    ],
    "observedArtifacts": [
      {
        "path": "assets/resource/ShiKong/reports/",
        "ownership": "preexisting_ignored",
        "cleanupAllowed": false
      },
      {
        "path": "src-tauri/target*/",
        "ownership": "preexisting_ignored",
        "cleanupAllowed": false
      },
      {
        "path": ".codex-window-*.png",
        "ownership": "preexisting_ignored_unknown",
        "cleanupAllowed": false
      }
    ]
  },
  "eventTail": {
    "seq": 323,
    "id": "EVT-0323",
    "hash": "sha256:accf1b42c0f3fdbec924ff6e97fb69673d812acc8a4a5cb2b1605d6058a8486a"
  },
  "evidenceTail": {
    "seq": 121,
    "id": "EVD-0121",
    "hash": "sha256:4a98a00dff22e38433cf221ac71b1012a3d5b8afb65dbd5d416b267765e1bb5e"
  },
  "checkpointCounter": 26,
  "lastCheckpoint": {
    "id": "CP-0026",
    "type": "state_snapshot",
    "path": "docs/execution/checkpoints/CP-0026-p3-s5-gates-and-verified-head.json",
    "createdAt": "2026-07-13T09:11:56Z",
    "safeToResume": true,
    "safeToRunLiveInput": false,
    "hash": "sha256:dd58d53a25f031f653ccac8c1fe3c00b80453f2e3c212f74bfe68c4778f32258"
  },
  "resume": {
    "blockers": [
      "P2 UI 切片需要启动本任务构建的本地应用；externalAuthorization=appdata_backup_only 不包含进程启动"
    ],
    "nextCommands": [
      "npm run execution:resume-check"
    ],
    "doNotDo": [
      "未扩展授权前不启动/停止应用、不发送游戏输入、不改写 AppData、不 commit/push"
    ],
    "lastSafeResumeSnapshotId": "CP-0026"
  },
  "completedSlices": [
    {
      "id": "P1-S1",
      "title": "禁止空队列误跑并原子占位前端 session",
      "status": "verified",
      "startedAt": "2026-07-11T07:55:40Z",
      "scope": [
        "src/main.js 与新的运行派发纯核心/测试"
      ],
      "nonGoals": [
        "本切片不实现 Rust per-HWND actor、OCR deadline 或真实输入"
      ],
      "safetyBoundaries": [
        "不启动应用、不发送游戏输入；仅静态测试和构建"
      ],
      "acceptanceCriteria": [
        {
          "id": "P1-S1-C1",
          "text": "没有启用队列的窗口不会回退执行当前激活任务",
          "status": "passed",
          "evidenceIds": [
            "EVD-0040",
            "EVD-0041",
            "EVD-0044",
            "EVD-0047"
          ],
          "requiredEvidenceCategories": [
            "test"
          ]
        },
        {
          "id": "P1-S1-C2",
          "text": "同一 HWND 在首个异步身份读取前已原子占位，快速重复启动只保留一个 session",
          "status": "passed",
          "evidenceIds": [
            "EVD-0040",
            "EVD-0041",
            "EVD-0044",
            "EVD-0047"
          ],
          "requiredEvidenceCategories": [
            "test"
          ]
        },
        {
          "id": "P1-S1-C3",
          "text": "当前工作树 Node 回归与 Vite 构建通过",
          "status": "passed",
          "evidenceIds": [
            "EVD-0040",
            "EVD-0041",
            "EVD-0042",
            "EVD-0043",
            "EVD-0044",
            "EVD-0045",
            "EVD-0046",
            "EVD-0047",
            "EVD-0048",
            "EVD-0049"
          ],
          "requiredEvidenceCategories": [
            "build",
            "test"
          ]
        }
      ],
      "nextAction": "开始 P1-S2 Rust per-HWND lane 与 cancel/deadline 骨架",
      "phaseId": "P1",
      "verifiedAt": "2026-07-11T08:31:09Z"
    },
    {
      "id": "P1-S2",
      "title": "Rust per-HWND lane 与 cancel/deadline 骨架",
      "status": "verified",
      "startedAt": "2026-07-11T08:31:09Z",
      "scope": [
        "src-tauri/src/runtime/、Tauri state/command DTO 和前端 cancel 调用契约"
      ],
      "nonGoals": [
        "本切片不改模板匹配算法、不启动应用、不发送真实输入"
      ],
      "safetyBoundaries": [
        "所有并发测试使用内存假任务；不调用 platform 输入函数"
      ],
      "acceptanceCriteria": [
        {
          "id": "P1-S2-C1",
          "text": "同一 HWND 并发请求最大执行数为 1，且按进入顺序串行",
          "status": "passed",
          "evidenceIds": [
            "EVD-0055"
          ],
          "requiredEvidenceCategories": [
            "test"
          ]
        },
        {
          "id": "P1-S2-C2",
          "text": "不同 HWND 的请求可以并行执行",
          "status": "passed",
          "evidenceIds": [
            "EVD-0055"
          ],
          "requiredEvidenceCategories": [
            "test"
          ]
        },
        {
          "id": "P1-S2-C3",
          "text": "排队请求可在执行前因 session cancel 或 deadline 到期而 fail-closed",
          "status": "passed",
          "evidenceIds": [
            "EVD-0055"
          ],
          "requiredEvidenceCategories": [
            "test"
          ]
        },
        {
          "id": "P1-S2-C4",
          "text": "Rust fmt/check/test/clippy 通过且真实输入测试保持 ignored",
          "status": "passed",
          "evidenceIds": [
            "EVD-0055"
          ],
          "requiredEvidenceCategories": [
            "build",
            "test"
          ]
        }
      ],
      "nextAction": "开始 P1-S3：为运行中的模板匹配增加有界 deadline/cancel 检查，保证超时或取消后零输入",
      "phaseId": "P1",
      "verifiedAt": "2026-07-11T09:42:32Z"
    },
    {
      "id": "P1-S3",
      "title": "运行中模板匹配取消与零输入提交边界",
      "status": "verified",
      "startedAt": "2026-07-11T09:42:32Z",
      "scope": [
        "src-tauri/src/runtime/、模板匹配与输入 dispatch、对应静态审计和纯内存测试"
      ],
      "nonGoals": [
        "本切片不实现 WinRT OCR 调用中止、不启动应用、不发送真实输入"
      ],
      "safetyBoundaries": [
        "所有新增测试使用内存 frame、fake closure 和计数器，不调用 platform 输入"
      ],
      "acceptanceCriteria": [
        {
          "id": "P1-S3-C1",
          "text": "模板匹配在搜索过程中响应 cancel/deadline 并立即失败",
          "status": "passed",
          "evidenceIds": [
            "EVD-0062"
          ],
          "requiredEvidenceCategories": [
            "test"
          ]
        },
        {
          "id": "P1-S3-C2",
          "text": "cancel/deadline 先于输入提交时 fake input counter 保持 0",
          "status": "passed",
          "evidenceIds": [
            "EVD-0062"
          ],
          "requiredEvidenceCategories": [
            "test"
          ]
        },
        {
          "id": "P1-S3-C3",
          "text": "所有输入 dispatch 通过线性化 commit_input，模板循环含周期 checkpoint",
          "status": "passed",
          "evidenceIds": [
            "EVD-0057",
            "EVD-0060"
          ],
          "requiredEvidenceCategories": [
            "test"
          ]
        },
        {
          "id": "P1-S3-C4",
          "text": "Rust fmt/check/test/clippy、Node、Python 审计和 Vite build 通过，真实输入测试保持 ignored",
          "status": "passed",
          "evidenceIds": [
            "EVD-0062"
          ],
          "requiredEvidenceCategories": [
            "test"
          ]
        }
      ],
      "nextAction": "开始 P1-S4：控制决策只允许 strict capture，移除桌面回退并标记 capture provider/reliability",
      "phaseId": "P1",
      "verifiedAt": "2026-07-11T10:50:27Z"
    },
    {
      "id": "P1-S4",
      "title": "严格捕获来源与预览信任边界",
      "status": "verified",
      "startedAt": "2026-07-11T10:50:27Z",
      "scope": [
        "platform capture policy、Preview/Snapshot/Step DTO、前端预览与目标验证、对应纯函数测试和静态审计"
      ],
      "nonGoals": [
        "本切片不把 Window GDI 标为 fully reliable，不实现 WGC/PrintWindow、旧帧检测或真实窗口验收"
      ],
      "safetyBoundaries": [
        "所有新增策略测试使用 fake capture closure/内存 frame，不调用真实 HWND 或输入"
      ],
      "acceptanceCriteria": [
        {
          "id": "P1-S4-C1",
          "text": "自动 snapshot、识图、OCR、保存和 live 断言只使用 strict target-window capture，无桌面回退",
          "status": "passed",
          "evidenceIds": [
            "EVD-0064",
            "EVD-0066"
          ],
          "requiredEvidenceCategories": [
            "test"
          ]
        },
        {
          "id": "P1-S4-C2",
          "text": "捕获 DTO 传播 provider、reliability、capturedAt、frameHash 和尺寸",
          "status": "passed",
          "evidenceIds": [
            "EVD-0064",
            "EVD-0066"
          ],
          "requiredEvidenceCategories": [
            "test"
          ]
        },
        {
          "id": "P1-S4-C3",
          "text": "strict primary 失败时不调用 desktop fallback，控制结果 fail-closed 且零输入",
          "status": "passed",
          "evidenceIds": [
            "EVD-0066"
          ],
          "requiredEvidenceCategories": [
            "test"
          ]
        },
        {
          "id": "P1-S4-C4",
          "text": "人工预览允许 fallback 但标记 preview_only，planned/preview_only 不得成为目标验证成功",
          "status": "passed",
          "evidenceIds": [
            "EVD-0063"
          ],
          "requiredEvidenceCategories": [
            "test"
          ]
        },
        {
          "id": "P1-S4-C5",
          "text": "Rust、Node、Python 审计和 Vite build 通过，真实输入测试保持 ignored",
          "status": "passed",
          "evidenceIds": [
            "EVD-0066"
          ],
          "requiredEvidenceCategories": [
            "test"
          ]
        }
      ],
      "nextAction": "开始 P1-S5：建立 OCR 有界 worker/队列和调用后 timeout/cancel 分类，不阻塞其它 HWND",
      "phaseId": "P1",
      "verifiedAt": "2026-07-11T11:45:02Z"
    },
    {
      "id": "P1-S5",
      "title": "OCR 有界 worker、backpressure 与超时分类",
      "status": "verified",
      "startedAt": "2026-07-11T11:45:02Z",
      "scope": [
        "src-tauri/src/runtime/ocr_pool.rs、OCR dispatch、前端失败分类、纯内存并发测试与静态审计"
      ],
      "nonGoals": [
        "本切片不强制终止 WinRT RecognizeAsync，不启用 health-verified capture，不启动应用或真实 OCR"
      ],
      "safetyBoundaries": [
        "所有 worker 测试执行内存 closure，不调用 Windows OCR、窗口捕获或输入"
      ],
      "acceptanceCriteria": [
        {
          "id": "P1-S5-C1",
          "text": "OCR pool 固定 2 workers、队列容量 8，满载时立即返回 ocr_queue_full",
          "status": "passed",
          "evidenceIds": [
            "EVD-0068",
            "EVD-0070"
          ],
          "requiredEvidenceCategories": [
            "test"
          ]
        },
        {
          "id": "P1-S5-C2",
          "text": "排队或等待 OCR 结果时 cancel/deadline 会停止等待并返回 cancelled/timeout",
          "status": "passed",
          "evidenceIds": [
            "EVD-0068",
            "EVD-0070"
          ],
          "requiredEvidenceCategories": [
            "test"
          ]
        },
        {
          "id": "P1-S5-C3",
          "text": "运行中 WinRT 任务迟到结果被丢弃，worker/线程数量保持有界",
          "status": "passed",
          "evidenceIds": [
            "EVD-0068",
            "EVD-0070"
          ],
          "requiredEvidenceCategories": [
            "test"
          ]
        },
        {
          "id": "P1-S5-C4",
          "text": "两个 OCR worker 可并行，不因单个慢任务阻塞其它 HWND",
          "status": "passed",
          "evidenceIds": [
            "EVD-0070"
          ],
          "requiredEvidenceCategories": [
            "test"
          ]
        },
        {
          "id": "P1-S5-C5",
          "text": "前端失败分类、静态审计、Rust/Node/Python/Vite 门禁通过，真实输入测试保持 ignored",
          "status": "passed",
          "evidenceIds": [
            "EVD-0067",
            "EVD-0068",
            "EVD-0070"
          ],
          "requiredEvidenceCategories": [
            "test"
          ]
        }
      ],
      "nextAction": "用户明确授予 local_app_run_owned_process_only 与 ui_read_only_test 后开始 P2-S1 默认视口工作台验收",
      "phaseId": "P1",
      "verifiedAt": "2026-07-11T12:36:19Z"
    },
    {
      "id": "P2-S1",
      "title": "工作台静态布局契约与默认视口可达性基线",
      "status": "verified",
      "startedAt": "2026-07-11T12:36:19Z",
      "scope": [
        "index.html,src/styles.css,src/main.js,src/workbench-layout-core.js,scripts/test_workbench_layout_core.mjs,scripts/audit_workbench_layout.py"
      ],
      "nonGoals": [
        "本切片不启动应用进程、不操作真实窗口；实际 1460x880 至 820x720 截图与交互验收留给 P2-S2"
      ],
      "safetyBoundaries": [
        "只修改仓库文件并运行 Node/Python/Vite；不启动 Tauri/Vite dev server"
      ],
      "acceptanceCriteria": [
        {
          "id": "P2-S1-C1",
          "text": "工作台具备命令栏、任务区、步骤区、检查器和底部运行区的稳定语义结构",
          "status": "passed",
          "evidenceIds": [
            "EVD-0072"
          ],
          "requiredEvidenceCategories": [
            "test"
          ]
        },
        {
          "id": "P2-S1-C2",
          "text": "默认与最小视口布局契约保证任务/步骤列表非零可用高度且无页面级横向滚动",
          "status": "passed",
          "evidenceIds": [
            "EVD-0071",
            "EVD-0072"
          ],
          "requiredEvidenceCategories": [
            "test"
          ]
        },
        {
          "id": "P2-S1-C3",
          "text": "检查器使用可达标签页，关键控件具备稳定尺寸和键盘焦点契约",
          "status": "passed",
          "evidenceIds": [
            "EVD-0071",
            "EVD-0072"
          ],
          "requiredEvidenceCategories": [
            "test"
          ]
        },
        {
          "id": "P2-S1-C4",
          "text": "布局 Node 测试、静态审计与现有全量前端回归通过",
          "status": "passed",
          "evidenceIds": [
            "EVD-0071",
            "EVD-0072"
          ],
          "requiredEvidenceCategories": [
            "test"
          ]
        }
      ],
      "nextAction": "创建 P2-S1 checkpoint，然后登记 P2-S2 五视口真实渲染与交互验收",
      "phaseId": "P2",
      "verifiedAt": "2026-07-11T13:06:16Z"
    },
    {
      "id": "P2-S2",
      "title": "五视口真实渲染与检查器交互验收",
      "status": "verified",
      "startedAt": "2026-07-11T13:06:16Z",
      "scope": [
        "index.html,src/styles.css,src/main.js,Playwright screenshots and viewport metrics"
      ],
      "nonGoals": [
        "本切片不启动 Tauri 应用、不读取或迁移真实 AppData、不枚举游戏窗口、不发送输入"
      ],
      "safetyBoundaries": [
        "只启动本任务拥有的 localhost 预览进程；完成后仅停止该 PID；浏览器只做只读 UI 交互"
      ],
      "acceptanceCriteria": [
        {
          "id": "P2-S2-C1",
          "text": "当前工作树 Vite 预览以可核验 PID/命令启动并可访问",
          "status": "passed",
          "evidenceIds": [
            "EVD-0077",
            "EVD-0081",
            "EVD-0084",
            "EVD-0087"
          ],
          "requiredEvidenceCategories": [
            "app_runtime",
            "test"
          ]
        },
        {
          "id": "P2-S2-C2",
          "text": "1460x880、1280x720、1120x720、920x680、820x720 均无页面级横向滚动且任务/步骤列表可达",
          "status": "passed",
          "evidenceIds": [
            "EVD-0077",
            "EVD-0081",
            "EVD-0084",
            "EVD-0087"
          ],
          "requiredEvidenceCategories": [
            "test"
          ]
        },
        {
          "id": "P2-S2-C3",
          "text": "检查器 tab 鼠标和键盘切换、补全定位与失败步骤定位能揭示正确面板",
          "status": "passed",
          "evidenceIds": [
            "EVD-0077",
            "EVD-0081",
            "EVD-0084",
            "EVD-0087"
          ],
          "requiredEvidenceCategories": [
            "test"
          ]
        },
        {
          "id": "P2-S2-C4",
          "text": "视觉发现的布局问题修复后 Node/Python/Vite 回归继续通过",
          "status": "passed",
          "evidenceIds": [
            "EVD-0078",
            "EVD-0079",
            "EVD-0080",
            "EVD-0082",
            "EVD-0083",
            "EVD-0085",
            "EVD-0086",
            "EVD-0088",
            "EVD-0089"
          ],
          "requiredEvidenceCategories": [
            "build",
            "test"
          ]
        }
      ],
      "nextAction": "Start P3 health-verified capture provider work",
      "blockers": [
        "缺少本地预览进程启动与只读 UI 测试授权"
      ],
      "phaseId": "P2",
      "verifiedAt": "2026-07-13T07:46:31Z"
    },
    {
      "id": "P3-S1",
      "title": "health-verified capture providers and black/stale frame gates",
      "status": "verified",
      "startedAt": "2026-07-13T07:46:31Z",
      "scope": [
        "src-tauri/src/platform.rs",
        "src-tauri/src/runtime/capture_health.rs",
        "src/capture-policy-core.js",
        "scripts/audit_capture_policy.py",
        "scripts/test_capture_policy_core.mjs"
      ],
      "nonGoals": [
        "Do not implement full OpenCV template engine in this slice",
        "Do not send live game input or migrate AppData",
        "Do not require Tauri app live window capture for slice close; unit/static proof is enough for provider health policy"
      ],
      "safetyBoundaries": [
        "Desktop capture remains preview-only and never authorizes control decisions",
        "Control capture fails closed on black, uniform, size-mismatch, or stale frames"
      ],
      "acceptanceCriteria": [
        {
          "id": "P3-S1-C1",
          "text": "Capture policy exposes health-verified target providers and never trusts desktop/preview frames for control",
          "status": "passed",
          "evidenceIds": [
            "EVD-0090",
            "EVD-0092"
          ],
          "requiredEvidenceCategories": [
            "source_audit",
            "test"
          ]
        },
        {
          "id": "P3-S1-C2",
          "text": "Black, uniform, size-mismatch, and stale frames are classified and block control decisions",
          "status": "passed",
          "evidenceIds": [
            "EVD-0090",
            "EVD-0092"
          ],
          "requiredEvidenceCategories": [
            "test"
          ]
        },
        {
          "id": "P3-S1-C3",
          "text": "PrintWindow/GDI strict capture path is covered by unit/static audits and fails closed without fallback for control",
          "status": "passed",
          "evidenceIds": [
            "EVD-0090",
            "EVD-0092"
          ],
          "requiredEvidenceCategories": [
            "test"
          ]
        },
        {
          "id": "P3-S1-C4",
          "text": "Node/Python capture audits and core regression remain green after the provider change",
          "status": "passed",
          "evidenceIds": [
            "EVD-0090",
            "EVD-0091",
            "EVD-0092",
            "EVD-0093"
          ],
          "requiredEvidenceCategories": [
            "build",
            "test"
          ]
        }
      ],
      "nextAction": "Continue P3 vision engine: ROI/template budget and fail-closed matching improvements",
      "phaseId": "P3",
      "verifiedAt": "2026-07-13T08:08:12Z"
    },
    {
      "id": "P3-S2",
      "title": "ROI-required template matching with search budget and fail-closed wait_image",
      "status": "verified",
      "startedAt": "2026-07-13T08:08:12Z",
      "scope": [
        "src-tauri/src/main.rs",
        "src-tauri/src/runtime/vision_match.rs",
        "src-tauri/src/runtime/mod.rs",
        "scripts/audit_capture_policy.py"
      ],
      "nonGoals": [
        "Do not integrate OpenCV in this slice",
        "Do not send live game input"
      ],
      "safetyBoundaries": [
        "wait_image/detect_page without template never report matched=true",
        "Unbudgeted full-frame brute-force search fails closed"
      ],
      "acceptanceCriteria": [
        {
          "id": "P3-S2-C1",
          "text": "wait_image without template returns missing_template and matched=false",
          "status": "passed",
          "evidenceIds": [
            "EVD-0094",
            "EVD-0095",
            "EVD-0096",
            "EVD-0098",
            "EVD-0099"
          ],
          "requiredEvidenceCategories": [
            "test"
          ]
        },
        {
          "id": "P3-S2-C2",
          "text": "template search enforces ROI/search budget and fails closed when over budget",
          "status": "passed",
          "evidenceIds": [
            "EVD-0094",
            "EVD-0095",
            "EVD-0096",
            "EVD-0098",
            "EVD-0099"
          ],
          "requiredEvidenceCategories": [
            "test"
          ]
        },
        {
          "id": "P3-S2-C3",
          "text": "match_template still supports cancel/deadline checkpoints and finds exact matches inside ROI",
          "status": "passed",
          "evidenceIds": [
            "EVD-0094",
            "EVD-0095",
            "EVD-0096",
            "EVD-0098",
            "EVD-0099"
          ],
          "requiredEvidenceCategories": [
            "test"
          ]
        },
        {
          "id": "P3-S2-C4",
          "text": "Rust vision unit tests and Node/Python core regression remain green",
          "status": "passed",
          "evidenceIds": [
            "EVD-0094",
            "EVD-0095",
            "EVD-0096",
            "EVD-0097",
            "EVD-0098",
            "EVD-0099",
            "EVD-0100"
          ],
          "requiredEvidenceCategories": [
            "build",
            "test"
          ]
        }
      ],
      "nextAction": "Begin P3-S3: frontend fail-closed for missing_template/search_budget and match box fields for overlay",
      "phaseId": "P3",
      "verifiedAt": "2026-07-13T08:21:44Z"
    },
    {
      "id": "P3-S3",
      "title": "Vision fail-closed taxonomy and match debug metadata",
      "status": "verified",
      "startedAt": "2026-07-13T08:21:44Z",
      "scope": [
        "src/main.js",
        "src/failure-evidence-core.js",
        "scripts/test_failure_evidence_core.mjs",
        "src-tauri/src/main.rs",
        "src-tauri/src/runtime/vision_match.rs"
      ],
      "nonGoals": [
        "Do not integrate OpenCV",
        "Do not send live game input",
        "Do not require full WGC implementation in this slice"
      ],
      "safetyBoundaries": [
        "missing_template and search_budget_exceeded never count as matched success",
        "Match debug metadata is observational only and never authorizes input"
      ],
      "acceptanceCriteria": [
        {
          "id": "P3-S3-C1",
          "text": "Frontend treats missing_template and search_budget_exceeded as fail-closed non-success statuses",
          "status": "passed",
          "evidenceIds": [
            "EVD-0101",
            "EVD-0102",
            "EVD-0104",
            "EVD-0105",
            "EVD-0107",
            "EVD-0108"
          ],
          "requiredEvidenceCategories": [
            "test"
          ]
        },
        {
          "id": "P3-S3-C2",
          "text": "Rust StepDispatchResult exposes match box fields when a template match is attempted",
          "status": "passed",
          "evidenceIds": [
            "EVD-0101",
            "EVD-0102",
            "EVD-0104",
            "EVD-0105",
            "EVD-0107",
            "EVD-0108"
          ],
          "requiredEvidenceCategories": [
            "test"
          ]
        },
        {
          "id": "P3-S3-C3",
          "text": "wait_image/detect_page without template remain missing_template with matched=false end-to-end in unit tests",
          "status": "passed",
          "evidenceIds": [
            "EVD-0101",
            "EVD-0102",
            "EVD-0104",
            "EVD-0105",
            "EVD-0107",
            "EVD-0108"
          ],
          "requiredEvidenceCategories": [
            "test"
          ]
        },
        {
          "id": "P3-S3-C4",
          "text": "Core regression and Vite build remain green",
          "status": "passed",
          "evidenceIds": [
            "EVD-0101",
            "EVD-0102",
            "EVD-0103",
            "EVD-0104",
            "EVD-0105",
            "EVD-0106",
            "EVD-0107",
            "EVD-0108",
            "EVD-0109"
          ],
          "requiredEvidenceCategories": [
            "build",
            "test"
          ]
        }
      ],
      "nextAction": "Begin P4-S1 offline home-vitality task scaffolding without live game input",
      "phaseId": "P3",
      "verifiedAt": "2026-07-13T08:40:13Z"
    },
    {
      "id": "P3-S4",
      "title": "Offline home-vitality readiness scaffolding",
      "status": "verified",
      "startedAt": "2026-07-13T08:40:13Z",
      "scope": [
        "src/home-vitality-core.js",
        "scripts/test_home_vitality_core.mjs",
        "src/main.js",
        "package.json"
      ],
      "nonGoals": [
        "Do not send live game input",
        "Do not require real HWND capture for slice close",
        "Do not integrate OpenCV"
      ],
      "safetyBoundaries": [
        "Offline readiness never authorizes live input",
        "Missing template/image targets remain fail-closed needs_capture"
      ],
      "acceptanceCriteria": [
        {
          "id": "P3-S4-C1",
          "text": "home-vitality blueprint reports step count and required visual targets offline",
          "status": "passed",
          "evidenceIds": [
            "EVD-0110",
            "EVD-0112"
          ],
          "requiredEvidenceCategories": [
            "test"
          ]
        },
        {
          "id": "P3-S4-C2",
          "text": "missing entry.home/template assets are classified needs_capture rather than ready",
          "status": "passed",
          "evidenceIds": [
            "EVD-0110",
            "EVD-0112"
          ],
          "requiredEvidenceCategories": [
            "test"
          ]
        },
        {
          "id": "P3-S4-C3",
          "text": "OCR/hotkey/restore steps classified without claiming live success",
          "status": "passed",
          "evidenceIds": [
            "EVD-0110",
            "EVD-0112"
          ],
          "requiredEvidenceCategories": [
            "test"
          ]
        },
        {
          "id": "P3-S4-C4",
          "text": "core regression and Vite build remain green",
          "status": "passed",
          "evidenceIds": [
            "EVD-0110",
            "EVD-0111",
            "EVD-0112",
            "EVD-0113"
          ],
          "requiredEvidenceCategories": [
            "build",
            "test"
          ]
        }
      ],
      "nextAction": "Optional: current-app launch gate prep; otherwise continue non-live polish or stop for handoff",
      "phaseId": "P3",
      "verifiedAt": "2026-07-13T08:48:21Z"
    }
  ]
}
